clicknium/__init__.py
clicknium/_clicknium.py
clicknium/locator.py
clicknium/.lib/automation/AWSSDK.Core.dll
clicknium/.lib/automation/AWSSDK.Core.xml
clicknium/.lib/automation/AWSSDK.S3.dll
clicknium/.lib/automation/AWSSDK.S3.xml
clicknium/.lib/automation/AWSSDK.SecurityToken.dll
clicknium/.lib/automation/AWSSDK.SecurityToken.xml
clicknium/.lib/automation/BouncyCastle.Crypto.dll
clicknium/.lib/automation/BouncyCastle.Crypto.xml
clicknium/.lib/automation/Clicknium.Common.dll
clicknium/.lib/automation/Clicknium.CredentialManager.dll
clicknium/.lib/automation/Clicknium.Desktop.Common.Logical.dll
clicknium/.lib/automation/Clicknium.Desktop.Core.dll
clicknium/.lib/automation/Clicknium.Desktop.Core.dll.config
clicknium/.lib/automation/Clicknium.Desktop.IA.dll
clicknium/.lib/automation/Clicknium.Desktop.Sap.dll
clicknium/.lib/automation/Clicknium.Desktop.Uia.dll
clicknium/.lib/automation/Clicknium.Desktop.Uia.dll.config
clicknium/.lib/automation/Clicknium.Driver.dll
clicknium/.lib/automation/Clicknium.Driver.dll.config
clicknium/.lib/automation/Clicknium.Java.ExtensionInstaller.exe
clicknium/.lib/automation/Clicknium.Java.ExtensionInstaller.exe.config
clicknium/.lib/automation/Clicknium.Java.dll
clicknium/.lib/automation/Clicknium.LocatorStore.Cloud.dll
clicknium/.lib/automation/Clicknium.LocatorStore.Cloud.dll.config
clicknium/.lib/automation/Clicknium.LocatorStore.Common.dll
clicknium/.lib/automation/Clicknium.LocatorStore.Local.dll
clicknium/.lib/automation/Clicknium.LocatorStore.dll
clicknium/.lib/automation/Clicknium.LocatorStore.dll.config
clicknium/.lib/automation/Clicknium.Logger.dll
clicknium/.lib/automation/Clicknium.Presentation.Common.dll
clicknium/.lib/automation/Clicknium.Recorder.exe
clicknium/.lib/automation/Clicknium.Recorder.exe.config
clicknium/.lib/automation/Clicknium.TurnOnWebExtension.dll
clicknium/.lib/automation/Clicknium.Web.Cdp.dll
clicknium/.lib/automation/Clicknium.Web.Cdp.dll.config
clicknium/.lib/automation/Clicknium.Web.Chromium.dll
clicknium-0.2.5.dist-info/licenses/LICENSE.txt
clicknium-0.2.5.dist-info/METADATA
clicknium-0.2.5.dist-info/WHEEL
clicknium-0.2.5.dist-info/top_level.txt
clicknium-0.2.5.dist-info/RECORD
