Metadata-Version: 2.4
Name: clicknium
Version: 0.2.5
Summary: Python package which enables GUI automation for all type of applications.
Home-page: https://www.clicknium.com/documents
Author: Clicknium
Author-email: clicknium@clicknium.com
Project-URL: Documentation, https://www.clicknium.com/documents
Classifier: Environment :: Win32 (MS Windows)
Classifier: Programming Language :: Python :: 3.7
Classifier: Programming Language :: Python :: 3.8
Classifier: Programming Language :: Python :: 3.9
Classifier: Programming Language :: Python :: 3.10
Classifier: License :: OSI Approved :: Apache Software License
Classifier: Operating System :: Microsoft :: Windows
License-File: LICENSE.txt
Requires-Dist: pythonnet>=3.0.0rc1
Requires-Dist: typing_extensions
Requires-Dist: requests
Requires-Dist: psutil
Dynamic: author
Dynamic: author-email
Dynamic: classifier
Dynamic: description
Dynamic: description-content-type
Dynamic: home-page
Dynamic: license-file
Dynamic: project-url
Dynamic: requires-dist
Dynamic: summary
